wfnsympy/optimize.py
wfnsympy/__init__.py
wfnsympy/QSYMLIB.cpython-37m-darwin.so
wfnsympy/file_io.py
wfnsympy/errors.py
wfnsympy/WFNSYMLIB.cpython-37m-darwin.so
wfnsympy/.dylibs/libgfortran.5.dylib
wfnsympy/.dylibs/libquadmath.0.dylib
wfnsympy/.dylibs/libgcc_s.1.1.dylib
wfnsympy-0.3.5.dist-info/RECORD
wfnsympy-0.3.5.dist-info/LICENSE
wfnsympy-0.3.5.dist-info/WHEEL
wfnsympy-0.3.5.dist-info/top_level.txt
wfnsympy-0.3.5.dist-info/METADATA
